abstcal/__init__.py
abstcal/abstcal_utils.py
abstcal/abstinence_calculator.py
abstcal/calculator_data.py
abstcal/calculator_error.py
abstcal/calculator_web_app.py
abstcal/calculator_web_utils.py
abstcal/tlfb_data.py
abstcal/visit_data.py
abstcal-0.9.dist-info/LICENSE.txt
abstcal-0.9.dist-info/METADATA
abstcal-0.9.dist-info/WHEEL
abstcal-0.9.dist-info/top_level.txt
abstcal-0.9.dist-info/RECORD
