Metadata-Version: 2.1
Name: abstcal
Version: 0.9
Summary: Calculate abstinence using the timeline followback data in substance research.
Home-page: https://github.com/ycui1-mda/abstcal
Author: Yong Cui
Author-email: ycui1@mdanderson.org
Classifier: Programming Language :: Python :: 3
Classifier: License :: OSI Approved :: MIT License
Classifier: Operating System :: OS Independent
Requires-Python: >=3.6
License-File: LICENSE.txt
Requires-Dist: pandas
Requires-Dist: numpy
Requires-Dist: matplotlib
Requires-Dist: seaborn
Requires-Dist: streamlit
Requires-Dist: openpyxl
Requires-Dist: xlrd
